kuflow_rest/__init__.py
kuflow_rest/_generated/__init__.py
kuflow_rest/_generated/_client.py
kuflow_rest/_generated/_configuration.py
kuflow_rest/_generated/_patch.py
kuflow_rest/_generated/_serialization.py
kuflow_rest/_generated/_version.py
kuflow_rest/_generated/aio/__init__.py
kuflow_rest/_generated/aio/_client.py
kuflow_rest/_generated/aio/_configuration.py
kuflow_rest/_generated/aio/_patch.py
kuflow_rest/_generated/aio/operations/__init__.py
kuflow_rest/_generated/aio/operations/_authentication_operations.py
kuflow_rest/_generated/aio/operations/_group_operations.py
kuflow_rest/_generated/aio/operations/_kms_operations.py
kuflow_rest/_generated/aio/operations/_patch.py
kuflow_rest/_generated/aio/operations/_principal_operations.py
kuflow_rest/_generated/aio/operations/_process_item_operations.py
kuflow_rest/_generated/aio/operations/_process_operations.py
kuflow_rest/_generated/aio/operations/_robot_operations.py
kuflow_rest/_generated/aio/operations/_tenant_operations.py
kuflow_rest/_generated/aio/operations/_tenant_user_operations.py
kuflow_rest/_generated/aio/operations/_worker_operations.py
kuflow_rest/_generated/models/__init__.py
kuflow_rest/_generated/models/_enums.py
kuflow_rest/_generated/models/_models.py
kuflow_rest/_generated/models/_patch.py
kuflow_rest/_generated/operations/__init__.py
kuflow_rest/_generated/operations/_authentication_operations.py
kuflow_rest/_generated/operations/_group_operations.py
kuflow_rest/_generated/operations/_kms_operations.py
kuflow_rest/_generated/operations/_patch.py
kuflow_rest/_generated/operations/_principal_operations.py
kuflow_rest/_generated/operations/_process_item_operations.py
kuflow_rest/_generated/operations/_process_operations.py
kuflow_rest/_generated/operations/_robot_operations.py
kuflow_rest/_generated/operations/_tenant_operations.py
kuflow_rest/_generated/operations/_tenant_user_operations.py
kuflow_rest/_generated/operations/_worker_operations.py
kuflow_rest/_generated/py.typed
kuflow_rest-3.2.1.dist-info/METADATA
kuflow_rest-3.2.1.dist-info/WHEEL
kuflow_rest-3.2.1.dist-info/RECORD
