Metadata-Version: 2.3
Name: kuflow-rest
Version: 3.2.1
Summary: Client for KuFlow Rest Api
License: MIT
Author: KuFlow S.L.
Author-email: kuflow@kuflow.com
Requires-Python: >=3.9,<4.0
Classifier: License :: OSI Approved :: MIT License
Classifier: Programming Language :: Python :: 3
Classifier: Programming Language :: Python :: 3.9
Classifier: Programming Language :: Python :: 3.10
Classifier: Programming Language :: Python :: 3.11
Classifier: Programming Language :: Python :: 3.12
Classifier: Programming Language :: Python :: 3.13
Requires-Dist: azure-core (>=1.30.2,<2.0.0)
Requires-Dist: isodate (>=0.6.1,<0.7.0)
Project-URL: Documentation, https://docs.kuflow.com/
Project-URL: Homepage, https://kuflow.com/
Project-URL: Repository, https://github.com/kuflow/kuflow-sdk-python
